{
  "generated": "2026-06-19T04:27:45.727Z",
  "events": [
    {
      "id": "commit-4fc683f",
      "title": "chore(crypto): evening signal update 2026-06-18",
      "type": "system",
      "datetime": "2026-06-18T17:30:09-04:00",
      "status": "completed",
      "description": "chore(crypto): evening signal update 2026-06-18",
      "metadata": {
        "commitHash": "4fc683f"
      }
    },
    {
      "id": "commit-81f96a6",
      "title": "chore(crypto): morning signal update 2026-06-18",
      "type": "system",
      "datetime": "2026-06-18T07:00:08-04:00",
      "status": "completed",
      "description": "chore(crypto): morning signal update 2026-06-18",
      "metadata": {
        "commitHash": "81f96a6"
      }
    },
    {
      "id": "commit-88abd33",
      "title": "chore: daily tracker scan 2026-06-17",
      "type": "system",
      "datetime": "2026-06-18T00:27:27-04:00",
      "status": "completed",
      "description": "chore: daily tracker scan 2026-06-17",
      "metadata": {
        "commitHash": "88abd33"
      }
    },
    {
      "id": "commit-1327e65",
      "title": "chore(crypto): evening signal update 2026-06-17",
      "type": "system",
      "datetime": "2026-06-17T17:30:08-04:00",
      "status": "completed",
      "description": "chore(crypto): evening signal update 2026-06-17",
      "metadata": {
        "commitHash": "1327e65"
      }
    },
    {
      "id": "commit-fdfd3da",
      "title": "chore(crypto): morning signal update 2026-06-17",
      "type": "system",
      "datetime": "2026-06-17T07:00:08-04:00",
      "status": "completed",
      "description": "chore(crypto): morning signal update 2026-06-17",
      "metadata": {
        "commitHash": "fdfd3da"
      }
    }
  ],
  "stats": {
    "totalEvents": 5,
    "completedEvents": 5,
    "scheduledEvents": 0,
    "deploymentsThisWeek": 5,
    "upcomingCronJobs": 0
  }
}